etextedit/README.md
etextedit/etextedit.py
etextedit/requirements.txt
etextedit/etextedit_plugins/Change to Lower Cases.py
etextedit/etextedit_plugins/Change to Upper Cases.py
etextedit-1.0.6.dist-info/METADATA
etextedit-1.0.6.dist-info/WHEEL
etextedit-1.0.6.dist-info/entry_points.txt
etextedit-1.0.6.dist-info/top_level.txt
etextedit-1.0.6.dist-info/RECORD
