Metadata-Version: 2.1
Name: etextedit
Version: 1.0.6
Summary: eTextEdit, a lightweight text editor built on prompt-toolkit
Home-page: https://letmedoit.ai
Author: Eliran Wong
Author-email: support@toolmate.ai
License: GNU General Public License (GPL)
Project-URL: Source, https://github.com/eliranwong/eTextEdit
Project-URL: Tracker, https://github.com/eliranwong/eTextEdit/issues
Project-URL: Documentation, https://github.com/eliranwong/eTextEdit/wiki
Project-URL: Funding, https://www.paypal.com/paypalme/toolmate
Keywords: text editor prompt toolkit
Classifier: Development Status :: 5 - Production/Stable
Classifier: Intended Audience :: End Users/Desktop
Classifier: Topic :: Utilities
Classifier: License :: OSI Approved :: GNU General Public License v3 or later (GPLv3+)
Classifier: Programming Language :: Python :: 3.7
Classifier: Programming Language :: Python :: 3.8
Classifier: Programming Language :: Python :: 3.9
Classifier: Programming Language :: Python :: 3.10
Classifier: Programming Language :: Python :: 3.11
Classifier: Programming Language :: Python :: 3.12
Requires-Python: >=3.7
Requires-Dist: datetime
Requires-Dist: prompt-toolkit
Requires-Dist: pygments
Requires-Dist: pyperclip
